hockey
setup.py
hockeylib/__init__.py
hockeylib/api.py
hockeylib/app.py
hockeylib/crash.py
hockeylib/version.py
hockeylib.egg-info/PKG-INFO
hockeylib.egg-info/SOURCES.txt
hockeylib.egg-info/dependency_links.txt
hockeylib.egg-info/requires.txt
hockeylib.egg-info/top_level.txt