Metadata-Version: 1.0
Name: hockeylib
Version: 0.1.0
Summary: A simple collection of hockey app api tools
Home-page: UNKNOWN
Author: Benjamin Wallis
Author-email: ben.nat.wallis@gmail.com
License: BSD
Keywords: hockeyapp
Platform: UNKNOWN
